tests/__init__.py
tests/conftest.py
tests/test_chats.py
tests/test_delete_message.py
tests/test_get_chats_history.py
tests/test_get_user.py
tests/test_send_message.py
wapchita/__init__.py
wapchita/answering.py
wapchita/async_tools.py
wapchita/client.py
wapchita/typings.py
wapchita/utils.py
wapchita/_api/__init__.py
wapchita/_api/headers.py
wapchita/_api/request_wap.py
wapchita/_api/urls.py
wapchita/_api/utils.py
wapchita/_api/endpoints/__init__.py
wapchita/_api/endpoints/contacts.py
wapchita/_api/endpoints/create_contact.py
wapchita/_api/endpoints/delete_message.py
wapchita/_api/endpoints/device_by_id.py
wapchita/_api/endpoints/download_file.py
wapchita/_api/endpoints/edit_message.py
wapchita/_api/endpoints/get_chat_details.py
wapchita/_api/endpoints/get_chats.py
wapchita/_api/endpoints/group_chats.py
wapchita/_api/endpoints/mark_as_unread.py
wapchita/_api/endpoints/search_chat.py
wapchita/_api/endpoints/send_message.py
wapchita/_api/endpoints/update_chat_labels.py
wapchita/_api/endpoints/upload_file.py
wapchita/models/__init__.py
wapchita/models/chats.py
wapchita/models/device.py
wapchita/models/user.py
wapchita/models/webhook.py
wapchita/models/_extras/__init__.py
wapchita/models/_extras/_chats.py
wapchita/models/_extras/_user.py
wapchita/models/_extras/_webhook.py
wapchita-0.1.8.dist-info/LICENSE
wapchita-0.1.8.dist-info/METADATA
wapchita-0.1.8.dist-info/WHEEL
wapchita-0.1.8.dist-info/top_level.txt
wapchita-0.1.8.dist-info/RECORD
