Metadata-Version: 2.1
Name: wapchita
Version: 0.1.8
Summary: Python SDK para la API de Wapchita https://wapchita.com/.
Home-page: https://pypi.org/project/wapchita/
Author: Alejo Prieto Dávalos
Author-email: alejoprietodavalos@gmail.com
Project-URL: Source, https://github.com/AlejoPrietoDavalos/wapchita/
Requires-Python: >=3.11
License-File: LICENSE
Requires-Dist: requests>=2.32
Requires-Dist: pydantic>=2.8
Requires-Dist: tenacity>=8.4.0
Requires-Dist: httpx>=0.27.0
Requires-Dist: requestsdantic>=0.0.3
